xestore/__init__.py
xestore/api/app.py
xestore/api/domain/documents.yml
xestore/api/domain/files.yml
xestore/api/secrets.py
xestore/api/server.py
xestore/api/settings.py
xestore/api/utils.py
xestore/cli.py
xestore/client/__init__.py
xestore/client/auth.py
xestore/client/frontend.py
xestore/client/http_client.py
xestore/settings.py
xestore-0.1.1.dist-info/entry_points.txt
xestore-0.1.1.dist-info/LICENSE
xestore-0.1.1.dist-info/WHEEL
xestore-0.1.1.dist-info/METADATA
xestore-0.1.1.dist-info/RECORD
