Metadata-Version: 2.1
Name: xestore
Version: 0.1.1
Summary: Top-level package for xestore.
Home-page: https://github.com/jmosbacher/xestore
License: MIT
Author: Yossi Mosbacher
Author-email: joe.mosbacher@gmail.com
Requires-Python: >=3.6,<4.0
Classifier: Development Status :: 2 - Pre-Alpha
Classifier: Intended Audience :: Developers
Classifier: License :: OSI Approved :: MIT License
Classifier: Natural Language :: English
Classifier: Programming Language :: Python :: 3
Classifier: Programming Language :: Python :: 3.6
Classifier: Programming Language :: Python :: 3.7
Classifier: Programming Language :: Python :: 3.8
Requires-Dist: click
Requires-Dist: eve-jwt (>=0.1.3,<0.2.0)
Requires-Dist: httpx (>=0.16.1,<0.17.0)
Requires-Dist: panel (>=0.10.2,<0.11.0)
